dlldiag/__init__.py
dlldiag/__main__.py
dlldiag/main.py
dlldiag/version.py
dlldiag/bin/x64/dlldiag-detour-loadlibrary.dll
dlldiag/bin/x64/dlldiag-helper-loadlibrary.exe
dlldiag/bin/x64/withdll.exe
dlldiag/bin/x86/dlldiag-detour-loadlibrary.dll
dlldiag/bin/x86/dlldiag-helper-loadlibrary.exe
dlldiag/bin/x86/withdll.exe
dlldiag/common/CommonErrors.py
dlldiag/common/DetourLibrary.py
dlldiag/common/FileIO.py
dlldiag/common/HelperProcess.py
dlldiag/common/ModuleHeader.py
dlldiag/common/OutputFormatting.py
dlldiag/common/StringUtils.py
dlldiag/common/WindowsApi.py
dlldiag/common/WindowsDebugger.py
dlldiag/common/__init__.py
dlldiag/subcommands/__init__.py
dlldiag/subcommands/deps.py
dlldiag/subcommands/docker.py
dlldiag/subcommands/graph.py
dlldiag/subcommands/trace.py
dll_diagnostics-0.0.18.dist-info/LICENSE
dll_diagnostics-0.0.18.dist-info/METADATA
dll_diagnostics-0.0.18.dist-info/WHEEL
dll_diagnostics-0.0.18.dist-info/entry_points.txt
dll_diagnostics-0.0.18.dist-info/top_level.txt
dll_diagnostics-0.0.18.dist-info/RECORD
