Metadata-Version: 2.1
Name: dll-diagnostics
Version: 0.0.18
Summary: Tools for diagnosing DLL dependency loading issues
Home-page: http://github.com/adamrehn/dll-diagnostics
Author: Adam Rehn
Author-email: adam@adamrehn.com
License: MIT
Keywords: dll windows containers
Platform: UNKNOWN
Classifier: License :: OSI Approved :: MIT License
Classifier: Programming Language :: Python :: 3.6
Classifier: Programming Language :: Python :: 3.7
Classifier: Programming Language :: Python :: 3.8
Classifier: Topic :: Software Development :: Build Tools
Classifier: Environment :: Console
Requires-Python: >=3.5
Requires-Dist: colorama
Requires-Dist: pefile
Requires-Dist: pywin32
Requires-Dist: networkx (>=2.5.1)
Requires-Dist: pydot (>=1.4.2)
Requires-Dist: setuptools (>=38.6.0)
Requires-Dist: termcolor
Requires-Dist: twine (>=1.11.0)
Requires-Dist: wheel (>=0.31.0)
